{
  "main": {
    "id": "a8df485ba316d30d",
    "type": "split",
    "children": [
      {
        "id": "9343e2cf222fa0e0",
        "type": "tabs",
        "children": [
          {
            "id": "9917339287480995",
            "type": "leaf",
            "state": {
              "type": "markdown",
              "state": {
                "file": "05_R_Week/Day2.md",
                "mode": "source",
                "source": false
              }
            }
          },
          {
            "id": "be91584199600591",
            "type": "leaf",
            "state": {
              "type": "release-notes",
              "state": {
                "currentVersion": "1.1.15"
              }
            }
          },
          {
            "id": "77be91b211a4a49b",
            "type": "leaf",
            "state": {
              "type": "markdown",
              "state": {
                "file": "07_Hypothesis_Testing/Day1.md",
                "mode": "source",
                "source": false
              }
            }
          }
        ],
        "currentTab": 2
      }
    ],
    "direction": "vertical"
  },
  "left": {
    "id": "806d41c50406c47f",
    "type": "split",
    "children": [
      {
        "id": "c6167548b7dd61a2",
        "type": "tabs",
        "children": [
          {
            "id": "ce0917bef73f47d2",
            "type": "leaf",
            "state": {
              "type": "file-explorer",
              "state": {
                "sortOrder": "alphabetical"
              }
            }
          },
          {
            "id": "4d11b95247b01269",
            "type": "leaf",
            "state": {
              "type": "search",
              "state": {
                "query": "",
                "matchingCase": false,
                "explainSearch": false,
                "collapseAll": false,
                "extraContext": false,
                "sortOrder": "alphabetical"
              }
            }
          },
          {
            "id": "c547dbe98fa08a7c",
            "type": "leaf",
            "state": {
              "type": "starred",
              "state": {}
            }
          }
        ]
      }
    ],
    "direction": "horizontal",
    "width": 200
  },
  "right": {
    "id": "1fc2bc29e1ae508a",
    "type": "split",
    "children": [
      {
        "id": "684917cab9c005e2",
        "type": "tabs",
        "children": [
          {
            "id": "88fe50cc4e7d0ca7",
            "type": "leaf",
            "state": {
              "type": "backlink",
              "state": {
                "file": "07_Hypothesis_Testing/Day1.md",
                "collapseAll": false,
                "extraContext": false,
                "sortOrder": "alphabetical",
                "showSearch": false,
                "searchQuery": "",
                "backlinkCollapsed": false,
                "unlinkedCollapsed": true
              }
            }
          },
          {
            "id": "2035033c33691f53",
            "type": "leaf",
            "state": {
              "type": "outgoing-link",
              "state": {
                "file": "07_Hypothesis_Testing/Day1.md",
                "linksCollapsed": false,
                "unlinkedCollapsed": true
              }
            }
          },
          {
            "id": "b24ce0ccf23167f3",
            "type": "leaf",
            "state": {
              "type": "tag",
              "state": {
                "sortOrder": "frequency",
                "useHierarchy": true
              }
            }
          },
          {
            "id": "6a4ec68bd5c2263f",
            "type": "leaf",
            "state": {
              "type": "outline",
              "state": {
                "file": "07_Hypothesis_Testing/Day1.md"
              }
            }
          }
        ],
        "currentTab": 3
      }
    ],
    "direction": "horizontal",
    "width": 300,
    "collapsed": true
  },
  "left-ribbon": {
    "hiddenItems": {
      "switcher:Open quick switcher": false,
      "graph:Open graph view": false,
      "canvas:Create new canvas": false,
      "daily-notes:Open today's daily note": false,
      "templates:Insert template": false,
      "command-palette:Open command palette": false
    }
  },
  "active": "77be91b211a4a49b",
  "lastOpenFiles": [
    "ppts/Week 07 - Tuesday.pptx",
    "ppts/08 - Tuesday.pptx",
    "07_Hypothesis_Testing/Day2.md",
    "07_Hypothesis_Testing/Day1.md",
    "03_dispersion_and_the_z/day2.md",
    "06_Sampling_Intervals/Day1.md",
    "ppts/Week 06 - Tuesday.pptx",
    "ppts/~$Week 06 - Tuesday.pptx",
    "08_Spring_Break/day2.md",
    "08_Spring_Break/day1.md",
    "06_Sampling_Intervals/Day2.md",
    "06_Sampling_Intervals/examples.md",
    "ppts/06 - Tuesday.pptx",
    "ppts/~$06 - Tuesday.pptx",
    "05_R_Week/Day2.md",
    "05_R_Week/Day1.md",
    "05_R_Week/Readme.md",
    "02_Descriptives/day1.md",
    "04_Test_1/day1.md",
    "03_dispersion_and_the_z/day1.md",
    "04_Test_1/day2.md",
    "03_Z-Scores/day1.md",
    "images/normal.jpg.md"
  ]
}